Metadata-Version: 1.0
Name: zahoor-distributions
Version: 1.0
Summary: Gaussian and Binomial distributions
Home-page: UNKNOWN
Author: Zahoor Ahmad]
Author-email: ahmadzahoor555@gmail.com
License: UNKNOWN
Platform: UNKNOWN
